Metadata-Version: 1.0
Name: redisco
Version: 0.1.dev13
Summary: Python Containers and Simple Models for Redis
Home-page: http://github.com/iamteem/redisco
Author: Tim Medina
Author-email: iamteem@gmail.com
License: MIT
Keywords: Redis,model,container
Platform: UNKNOWN
Classifier: Development Status :: 2 - Pre-Alpha
Classifier: Environment :: Console
Classifier: Intended Audience :: Developers
Classifier: License :: OSI Approved :: MIT License
Classifier: Operating System :: OS Independent
Classifier: Programming Language :: Python
